LICENSE.txt
MelodyMaster/__init__.py
MelodyMaster/algorithm.py
MelodyMaster/api.py
MelodyMaster/cil/__init__.py
MelodyMaster/cil/_cil.py
MelodyMaster/client.py
MelodyMaster/converter.py
MelodyMaster/deprecated/__init__.py
MelodyMaster/deprecated/decorator.py
MelodyMaster/enums.py
MelodyMaster/exceptions.py
MelodyMaster/factory.py
MelodyMaster/factory_misc.py
MelodyMaster/interfaces/__init__.py
MelodyMaster/interfaces/client.py
MelodyMaster/loggers.py
MelodyMaster/MelodyMaster.py
MelodyMaster/misc.py
MelodyMaster/musix_match_api.py
MelodyMaster/Musix_spot.py
MelodyMaster/Muxis.py
MelodyMaster/schemas/__init__.py
MelodyMaster/schemas/album.py
MelodyMaster/schemas/artist/__init__.py
MelodyMaster/schemas/artist/views/__init__.py
MelodyMaster/schemas/artist/views/full_albums.py
MelodyMaster/schemas/artist/views/last_release.py
MelodyMaster/schemas/artist/views/simular_artists.py
MelodyMaster/schemas/artist/views/top_music.py
MelodyMaster/schemas/artist/views/top_song.py
MelodyMaster/schemas/artists.py
MelodyMaster/schemas/attributes.py
MelodyMaster/schemas/base.py
MelodyMaster/schemas/content_version.py
MelodyMaster/schemas/enums.py
MelodyMaster/schemas/errors.py
MelodyMaster/schemas/models.py
MelodyMaster/schemas/photos.py
MelodyMaster/schemas/play_params.py
MelodyMaster/schemas/playlist/__init__.py
MelodyMaster/schemas/playlist/playlist.py
MelodyMaster/schemas/urls.py
MelodyMaster/serializers.py
MelodyMaster/signature.py
MelodyMaster/tok.py
MelodyMaster/typehints.py
MelodyMaster/user_agent.py
MelodyMaster/utils.py
README.md
melodymaster-1.0.2.dist-info/entry_points.txt
melodymaster-1.0.2.dist-info/LICENSE.txt
melodymaster-1.0.2.dist-info/METADATA
melodymaster-1.0.2.dist-info/WHEEL
melodymaster-1.0.2.dist-info/RECORD
