Metadata-Version: 2.1
Name: MelodyMaster
Version: 1.0.2
Summary: Is a asynchronous framework from reverse engineered Shazam API written in Python 3.8+ with asyncio and aiohttp.
Home-page: https://github.com/BDXBB/MelodyMaster
License: MIT
Keywords: python,shazam,music,recognize,api,async,asyncio,aiohttp,identification
Author: BKXBB
Requires-Python: >=3.8,<4.0
Classifier: License :: OSI Approved :: MIT License
Classifier: Programming Language :: Python :: 3
Classifier: Programming Language :: Python :: 3.8
Classifier: Programming Language :: Python :: 3.9
Classifier: Programming Language :: Python :: 3.10
Classifier: Programming Language :: Python :: 3.11
Classifier: Programming Language :: Python :: 3.12
Requires-Dist: SpeechRecognition (==3.10.4)
Requires-Dist: aiofiles (==23.2.1)
Requires-Dist: aiohttp (>=3.8.3,<4.0.0)
Requires-Dist: aiohttp-retry (>=2.8.3,<3.0.0)
Requires-Dist: anyio (==4.3.0)
Requires-Dist: dataclass-factory (==2.16)
Requires-Dist: numpy (>=1.24.0,<2.0.0)
Requires-Dist: pydantic (>=1.10.2,<2.0.0)
Requires-Dist: pydub (>=0.25.1,<0.26.0)
Requires-Dist: shazamio-core (>=1.0.7,<2.0.0)
Project-URL: Repository, https://github.com/BDXBB/MelodyMaster
